Workbook

Sheet Сводка
A1: ООО «Хэнд-маркетинг» · предложение для вендор-листа ГК «Киевская площадь»
A2: Заказчик: ООО «Центральная Площадь», ИНН 7730338370. Срок подачи: 23.10.2026.
A4: Общие условия
A5: Оказываем направлений | B5: =COUNTIF(C18:C48,"Оказываем")&" из 31"
A6: Стоимость работ | B6: По каждой позиции на листе «КП», ставки на листе «Прайс»
A7: НДС | B7: ="Цены без НДС. НДС "&TEXT(Прайс!$B$5,"0%")&" начисляется сверху"
A8: Скидка | B8: ="Скидка участника вендор-листа "&TEXT(Прайс!$B$6,"0%")&" на работу агентства уже в КП: креатив, дизайн, тексты, CGI, фото- и видеосъемка, продюсирование, концепции, эскизы, агентская комиссия. На производство, тиражи и закупки скидку даем от объема конкретного заказа."
A9: Условия оплаты: услуги | B9: ="100% по факту, оплата в течение "&Прайс!$B$8&" р.д. после акта, без аванса"
A10: Условия оплаты: услуги с расходами на подрядчиков | B10: ="Аванс "&TEXT(Прайс!$B$11,"0%")&" на расходы подрядчиков, остаток в течение "&Прайс!$B$8&" р.д. после акта"
A11: Условия оплаты: производство, закупки, мероприятия | B11: ="Аванс "&TEXT(Прайс!$B$7,"0%")&", остаток "&TEXT(1-Прайс!$B$7,"0%")&" после акта"
A12: Фиксация цен | B12: ="Работа агентства: "&Прайс!$B$9&" мес. с даты КП. Производство и закупки: "&Прайс!$B$10&" мес. с даты КП, дальше пересчет по ценам поставщиков"
A13: Юрлица холдинга | B13: Один закрепленный менеджер и одинаковые условия для всех 7 юрлиц из письма № 38/2026
A14: Менеджер | B14: Народецкий Александр, Client Service Director, +7 985 999 87 83, anarodetsky@hand-marketing.ru
A16: Направления
A17: № | B17: Направление | C17: Участие | D17: Итог расчета по запросу ТЗ со скидкой, руб. без НДС | E17: Условия оплаты | F17: Фиксация
A18: 1 | B18: Рекламно-производственное агентство | C18: Оказываем | D18: Часть расчетов по запросу, см. лист «КП» | E18: ="Аванс "&TEXT(Прайс!$B$7,"0%")&", остаток "&TEXT(1-Прайс!$B$7,"0%")&" после акта" | F18: =Прайс!$B$10&" мес."
A19: 2 | B19: Наружная реклама | C19: Не оказываем
A20: 3 | B20: Монтажные и демонтажные работы | C20: Оказываем | D20: =КП!J21 | E20: ="100% по факту, оплата в течение "&Прайс!$B$8&" р.д. после акта, без аванса" | F20: =Прайс!$B$9&" мес."
A21: 4 | B21: Альпинисты, высотные работы | C21: Не оказываем
A22: 5 | B22: Пластиковые карты | C22: Оказываем | D22: Несколько расчетов, см. лист «КП» | E22: ="Аванс "&TEXT(Прайс!$B$7,"0%")&", остаток "&TEXT(1-Прайс!$B$7,"0%")&" после акта" | F22: =Прайс!$B$10&" мес."
A23: 6 | B23: Брендированные вешалки | C23: Оказываем | D23: Несколько расчетов, см. лист «КП» | E23: ="Аванс "&TEXT(Прайс!$B$7,"0%")&", остаток "&TEXT(1-Прайс!$B$7,"0%")&" после акта" | F23: =Прайс!$B$10&" мес."
A24: 7 | B24: Брендированные тишью | C24: Оказываем | D24: Несколько расчетов, см. лист «КП» | E24: ="Аванс "&TEXT(Прайс!$B$7,"0%")&", остаток "&TEXT(1-Прайс!$B$7,"0%")&" после акта" | F24: =Прайс!$B$10&" мес."
A25: 8 | B25: Брендированные кофры | C25: Оказываем | D25: Несколько расчетов, см. лист «КП» | E25: ="Аванс "&TEXT(Прайс!$B$7,"0%")&", остаток "&TEXT(1-Прайс!$B$7,"0%")&" после акта" | F25: =Прайс!$B$10&" мес."
A26: 9 | B26: CGI & AI-студия, CGI-ролики | C26: Оказываем | D26: =КП!J69 | E26: ="100% по факту, оплата в течение "&Прайс!$B$8&" р.д. после акта, без аванса" | F26: =Прайс!$B$9&" мес."
A27: 10 | B27: Брендинг | C27: Оказываем | D27: =КП!J77 | E27: ="100% по факту, оплата в течение "&Прайс!$B$8&" р.д. после акта, без аванса" | F27: =Прайс!$B$9&" мес."
A28: 11 | B28: Дизайн макетов | C28: Оказываем | D28: Несколько расчетов, см. лист «КП» | E28: ="100% по факту, оплата в течение "&Прайс!$B$8&" р.д. после акта, без аванса" | F28: =Прайс!$B$9&" мес."
A29: 12 | B29: Написание текстов | C29: Оказываем | D29: Несколько расчетов, см. лист «КП» | E29: ="100% по факту, оплата в течение "&Прайс!$B$8&" р.д. после акта, без аванса" | F29: =Прайс!$B$9&" мес."
A30: 13 | B30: Продюсер съемок | C30: Оказываем | D30: =КП!J95 | E30: ="Аванс "&TEXT(Прайс!$B$11,"0%")&" на расходы подрядчиков, остаток в течение "&Прайс!$B$8&" р.д. после акта" | F30: =Прайс!$B$9&" мес."
A31: 14 | B31: Фотограф | C31: Оказываем | D31: Несколько расчетов, см. лист «КП» | E31: ="100% по факту, оплата в течение "&Прайс!$B$8&" р.д. после акта, без аванса" | F31: =Прайс!$B$9&" мес."
A32: 15 | B32: Видеограф | C32: Оказываем | D32: Несколько расчетов, см. лист «КП» | E32: ="100% по факту, оплата в течение "&Прайс!$B$8&" р.д. после акта, без аванса" | F32: =Прайс!$B$9&" мес."
A33: 16 | B33: Мерч, корпоративные подарки | C33: Оказываем | D33: Часть расчетов по запросу, см. лист «КП» | E33: ="Аванс "&TEXT(Прайс!$B$7,"0%")&", остаток "&TEXT(1-Прайс!$B$7,"0%")&" после акта" | F33: =Прайс!$B$10&" мес."
A34: 17 | B34: Сувенирная продукция, PR-боксы | C34: Оказываем | D34: Часть расчетов по запросу, см. лист «КП» | E34: ="Аванс "&TEXT(Прайс!$B$7,"0%")&", остаток "&TEXT(1-Прайс!$B$7,"0%")&" после акта" | F34: =Прайс!$B$10&" мес."
A35: 18 | B35: Брендированная вода | C35: Оказываем | D35: Несколько расчетов, см. лист «КП» | E35: ="Аванс "&TEXT(Прайс!$B$7,"0%")&", остаток "&TEXT(1-Прайс!$B$7,"0%")&" после акта" | F35: =Прайс!$B$10&" мес."
A36: 19 | B36: Свечи и диффузоры | C36: Оказываем | D36: Несколько расчетов, см. лист «КП» | E36: ="Аванс "&TEXT(Прайс!$B$7,"0%")&", остаток "&TEXT(1-Прайс!$B$7,"0%")&" после акта" | F36: =Прайс!$B$10&" мес."
A37: 20 | B37: Шоколад | C37: Оказываем | D37: =КП!J174 | E37: ="Аванс "&TEXT(Прайс!$B$7,"0%")&", остаток "&TEXT(1-Прайс!$B$7,"0%")&" после акта" | F37: =Прайс!$B$10&" мес."
A38: 21 | B38: Форма для сотрудников | C38: Оказываем | D38: Несколько расчетов, см. лист «КП» | E38: ="Аванс "&TEXT(Прайс!$B$7,"0%")&", остаток "&TEXT(1-Прайс!$B$7,"0%")&" после акта" | F38: =Прайс!$B$10&" мес."
A39: 22 | B39: Агентство по организации мероприятий | C39: Оказываем | D39: =КП!J184 | E39: ="Аванс "&TEXT(Прайс!$B$7,"0%")&", остаток "&TEXT(1-Прайс!$B$7,"0%")&" после акта" | F39: =Прайс!$B$10&" мес."
A40: 23 | B40: Декорирование, флористика | C40: Оказываем | D40: Часть расчетов по запросу, см. лист «КП» | E40: ="Аванс "&TEXT(Прайс!$B$7,"0%")&", остаток "&TEXT(1-Прайс!$B$7,"0%")&" после акта" | F40: =Прайс!$B$10&" мес."
A41: 24 | B41: Кейтеринг | C41: Оказываем | D41: Несколько расчетов, см. лист «КП» | E41: ="Аванс "&TEXT(Прайс!$B$7,"0%")&", остаток "&TEXT(1-Прайс!$B$7,"0%")&" после акта" | F41: =Прайс!$B$10&" мес."
A42: 25 | B42: Звук и свет | C42: Оказываем | D42: =КП!J213 | E42: ="Аванс "&TEXT(Прайс!$B$11,"0%")&" на расходы подрядчиков, остаток в течение "&Прайс!$B$8&" р.д. после акта" | F42: =Прайс!$B$9&" мес."
A43: 26 | B43: Звукорежиссер | C43: Оказываем | D43: =КП!J221 | E43: ="Аванс "&TEXT(Прайс!$B$11,"0%")&" на расходы подрядчиков, остаток в течение "&Прайс!$B$8&" р.д. после акта" | F43: =Прайс!$B$9&" мес."
A44: 27 | B44: Диджей | C44: Оказываем | D44: Несколько расчетов, см. лист «КП» | E44: ="Аванс "&TEXT(Прайс!$B$11,"0%")&" на расходы подрядчиков, остаток в течение "&Прайс!$B$8&" р.д. после акта" | F44: =Прайс!$B$9&" мес."
A45: 28 | B45: Аренда мебели | C45: Оказываем | D45: =КП!J226 | E45: ="Аванс "&TEXT(Прайс!$B$7,"0%")&", остаток "&TEXT(1-Прайс!$B$7,"0%")&" после акта" | F45: =Прайс!$B$10&" мес."
A46: 29 | B46: Закупка мебели | C46: Оказываем | D46: По запросу, срок расчета на листе «КП» | E46: ="Аванс "&TEXT(Прайс!$B$7,"0%")&", остаток "&TEXT(1-Прайс!$B$7,"0%")&" после акта" | F46: =Прайс!$B$10&" мес."
A47: 30 | B47: Стажеры, персонал | C47: Оказываем | D47: Несколько расчетов, см. лист «КП» | E47: ="Аванс "&TEXT(Прайс!$B$11,"0%")&" на расходы подрядчиков, остаток в течение "&Прайс!$B$8&" р.д. после акта" | F47: =Прайс!$B$9&" мес."
A48: 31 | B48: Фотозона | C48: Оказываем | D48: По запросу, срок расчета на листе «КП» | E48: ="Аванс "&TEXT(Прайс!$B$7,"0%")&", остаток "&TEXT(1-Прайс!$B$7,"0%")&" после акта" | F48: =Прайс!$B$10&" мес."
A50: ООО «Хэнд-маркетинг» · ИНН 7709931482 · КПП 770901001 · ОГРН 1137746525608 · 123022, Москва, ул. Рочдельская, 14А · hand-marketing.ru

Sheet КП
A1: Коммерческое предложение ООО «Хэнд-маркетинг» · вендор-лист маркетинговых подрядчиков ГК «Киевская площадь»
A2: Объекты: ТРЦ «Ривьера», Центральный рынок, МФК «Венеция», ТЦ «Времена года», ТЦ «ЦДМ на Лубянке». Расчеты по запросам ТЗ. Цены в рублях без НДС, НДС 22% начисляется сверху. Доставка в расчетах по адресу: Москва, ул. Автозаводская, д. 18.
A4: № | B4: Направление | C4: Объекты | D4: Расчет по запросу ТЗ | E4: Ед. изм. | F4: Объем | G4: Цена за ед. по прайсу, руб. без НДС | H4: Стоимость по прайсу, руб. без НДС | I4: Скидка | J4: Стоимость со скидкой, руб. без НДС | K4: НДС 22%, руб. | L4: Итого с НДС, руб. | M4: Срок выполнения | N4: Условия оплаты | O4: Фиксация цены | P4: Примечание
A5: 1 | B5: Рекламно-производственное агентство | C5: Венеция, Ривьера | D5: Позиция ТЗ | N5: ="Аванс "&TEXT(Прайс!$B$7,"0%")&", остаток "&TEXT(1-Прайс!$B$7,"0%")&" после акта" | O5: =Прайс!$B$10&" мес." | P5: Объемные буквы считаем по макету: цену задают шрифт, борт и тип подсветки. Гарантия 12 мес. на конструкции, 12 мес. на электрику и подсветку. Ночной монтаж 23:00-07:00: плюс 30% к стоимости монтажа, в расчете лайтбокса уже учтен. Доставка до объекта в расчетах отдельной строкой. Замер бесплатно, выезд в течение 1 р.д.
D6: (1) Лайтбокс 1,2 × 1,8 м с монтажом на стену | E6: итого | H6: =SUM(H7:H10) | J6: =SUM(J7:J10) | K6: =SUM(K7:K10) | L6: =SUM(L7:L10) | M6: 7 р.д. производство, монтаж 1 ночь
D7: Лайтбокс односторонний 1,2 × 1,8 м, LED-подсветка, изготовление | E7: шт. | F7: 1 | G7: =Прайс!E17 | H7: =ROUND(F7*G7,0) | I7: 0 | J7: =ROUND(H7*(1-I7),0) | K7: =ROUND(J7*Прайс!$B$5,0) | L7: =J7+K7
D8: Монтаж лайтбокса на стену, подключение | E8: шт. | F8: 1 | G8: =Прайс!E18 | H8: =ROUND(F8*G8,0) | I8: 0 | J8: =ROUND(H8*(1-I8),0) | K8: =ROUND(J8*Прайс!$B$5,0) | L8: =J8+K8
D9: Доплата за ночной монтаж 23:00-07:00, 30% к монтажу | E9: компл. | F9: 1 | G9: =Прайс!E19 | H9: =ROUND(F9*G9,0) | I9: 0 | J9: =ROUND(H9*(1-I9),0) | K9: =ROUND(J9*Прайс!$B$5,0) | L9: =J9+K9 | P9: монтаж ночью
D10: Доставка конструкций на объект по Москве | E10: рейс | F10: 1 | G10: =Прайс!E20 | H10: =ROUND(F10*G10,0) | I10: 0 | J10: =ROUND(H10*(1-I10),0) | K10: =ROUND(J10*Прайс!$B$5,0) | L10: =J10+K10 | P10: до Автозаводской, 18
D11: (2) Объемные буквы 40 см, 10 знаков, монтаж на высоте 4 м | M11: Расчет за 2 р.д. после макета и замера
D12: Объемная буква с внутренней подсветкой, высота 40 см | E12: знак | F12: 10 | G12: По запросу | J12: По запросу | L12: По запросу
D13: Блок питания, коммутация, подложка вывески | E13: компл. | F13: 1 | G13: По запросу | J13: По запросу | L13: По запросу
D14: Монтаж вывески на высоте до 4 м, с вышкой | E14: компл. | F14: 1 | G14: По запросу | J14: По запросу | L14: По запросу
D15: (3) Витрина 3 × 2,5 м: пленка + 2 фигуры ПВХ | E15: итого | H15: =SUM(H16:H18) | J15: =SUM(J16:J18) | K15: =SUM(K16:K18) | L15: =SUM(L16:L18) | M15: 5 р.д. с монтажом
D16: Пленка с полноцветной печатью и ламинацией, оклейка витрины | E16: м² | F16: 7.5 | G16: =Прайс!E24 | H16: =ROUND(F16*G16,0) | I16: 0 | J16: =ROUND(H16*(1-I16),0) | K16: =ROUND(J16*Прайс!$B$5,0) | L16: =J16+K16 | P16: 3 × 2,5 м = 7,5 м², с оклейкой
D17: Напольная фигура ПВХ 5 мм до 1,8 м, полноцветная печать, опора | E17: шт. | F17: 2 | G17: =Прайс!E25 | H17: =ROUND(F17*G17,0) | I17: 0 | J17: =ROUND(H17*(1-I17),0) | K17: =ROUND(J17*Прайс!$B$5,0) | L17: =J17+K17
D18: Доставка конструкций на объект по Москве | E18: рейс | F18: 1 | G18: =Прайс!E20 | H18: =ROUND(F18*G18,0) | I18: 0 | J18: =ROUND(H18*(1-I18),0) | K18: =ROUND(J18*Прайс!$B$5,0) | L18: =J18+K18 | P18: фигуры, до Автозаводской, 18
A19: 2 | B19: Наружная реклама | C19: Времена Года, Венеция | D19: Не оказываем | P19: Направление не входит в наш профиль. Расчет не предоставляем.
A20: 3 | B20: Монтажные и демонтажные работы | C20: ЦДМ, Ривьера | D20: Позиция ТЗ | N20: ="100% по факту, оплата в течение "&Прайс!$B$8&" р.д. после акта, без аванса" | O20: =Прайс!$B$9&" мес." | P20: Ставка ночной смены уже ночная, доплата 30% к ней не применяется. Срочный выезд в течение 24 ч: плюс 25% к стоимости смен. Ручной инструмент входит в ставку, вышки по прайсу. Работаем по регламенту ТЦ: пропуска, ночной режим, вывоз мусора.
D21: Новогодний декор в атриуме: 4 монтажника, 2 ночные смены монтажа + 1 ночная смена демонтажа | E21: итого | H21: =SUM(H22:H25) | J21: =SUM(J22:J25) | K21: =SUM(K22:K25) | L21: =SUM(L22:L25) | M21: Выход по графику ТЦ, бригада до 12 человек на смену
D22: Монтажник, смена 8 ч, ночная | E22: чел.-смена | F22: 12 | G22: =Прайс!E28 | H22: =ROUND(F22*G22,0) | I22: 0 | J22: =ROUND(H22*(1-I22),0) | K22: =ROUND(J22*Прайс!$B$5,0) | L22: =J22+K22 | P22: 4 чел. × 3 смены
D23: Грузовой автомобиль до 3 т, рейс по Москве | E23: рейс | F23: 2 | G23: =Прайс!E29 | H23: =ROUND(F23*G23,0) | I23: 0 | J23: =ROUND(H23*(1-I23),0) | K23: =ROUND(J23*Прайс!$B$5,0) | L23: =J23+K23 | P23: завоз и вывоз
D24: Вывоз упаковки и мусора | E24: рейс | F24: 1 | G24: =Прайс!E30 | H24: =ROUND(F24*G24,0) | I24: 0 | J24: =ROUND(H24*(1-I24),0) | K24: =ROUND(J24*Прайс!$B$5,0) | L24: =J24+K24
D25: Аренда вышки-туры до 6 м с доставкой | E25: сутки | F25: 3 | G25: =Прайс!E31 | H25: =ROUND(F25*G25,0) | I25: 0 | J25: =ROUND(H25*(1-I25),0) | K25: =ROUND(J25*Прайс!$B$5,0) | L25: =J25+K25 | P25: на каждую ночь
A26: 4 | B26: Альпинисты, высотные работы | C26: Времена Года, ЦДМ | D26: Не оказываем | P26: Направление не входит в наш профиль. Расчет не предоставляем.
A27: 5 | B27: Пластиковые карты | C27: Венеция | D27: Позиция ТЗ | N27: ="Аванс "&TEXT(Прайс!$B$7,"0%")&", остаток "&TEXT(1-Прайс!$B$7,"0%")&" после акта" | O27: =Прайс!$B$10&" мес." | P27: Минимальный тираж 500 шт. Нумерация и кодировка полосы по вашему списку, проверяем на вашем считывателе до тиража. Дозаказ на тех же условиях, клише храним 12 месяцев.
D28: Подарочные карты, тираж 1 000 шт. | E28: итого | H28: =SUM(H29:H31) | J28: =SUM(J29:J31) | K28: =SUM(K29:K31) | L28: =SUM(L29:L31) | M28: 10 р.д. после утверждения образца, образец 5 р.д.
D29: Карта ПВХ 0,76 мм CR80, печать 4+4, матовая ламинация, фольга, HiCo, лазерная нумерация | E29: шт. | F29: 1000 | G29: =Прайс!E32 | H29: =ROUND(F29*G29,0) | I29: 0 | J29: =ROUND(H29*(1-I29),0) | K29: =ROUND(J29*Прайс!$B$5,0) | L29: =J29+K29
D30: Клише для тиснения фольгой, подготовка к печати | E30: компл. | F30: 1 | G30: =Прайс!E33 | H30: =ROUND(F30*G30,0) | I30: 0 | J30: =ROUND(H30*(1-I30),0) | K30: =ROUND(J30*Прайс!$B$5,0) | L30: =J30+K30
D31: Доставка тиража по Москве | E31: рейс | F31: 1 | G31: =Прайс!E35 | H31: =ROUND(F31*G31,0) | I31: 0 | J31: =ROUND(H31*(1-I31),0) | K31: =ROUND(J31*Прайс!$B$5,0) | L31: =J31+K31 | P31: до Автозаводской, 18
D32: Пробный образец | E32: компл. | F32: 1 | G32: =Прайс!E34 | H32: =ROUND(F32*G32,0) | I32: 0 | J32: =ROUND(H32*(1-I32),0) | K32: =ROUND(J32*Прайс!$B$5,0) | L32: =J32+K32 | M32: 5 р.д.
A33: 6 | B33: Брендированные вешалки | C33: Венеция | D33: Позиция ТЗ | N33: ="Аванс "&TEXT(Прайс!$B$7,"0%")&", остаток "&TEXT(1-Прайс!$B$7,"0%")&" после акта" | O33: =Прайс!$B$10&" мес." | P33: Тиражи 200 и 500: флок ближайшего цвета из наличия. Тираж 1 000: флок по Pantone брендбука. Логотип на гладкой вставке или тиснением по рекомендации производителя, проверяем на образце. Групповая упаковка с защитой крючков. Брак меняем за свой счет.
D34: Тираж 200 шт. | E34: итого | H34: =SUM(H35:H36) | J34: =SUM(J35:J36) | K34: =SUM(K35:K36) | L34: =SUM(L35:L36) | M34: 15 р.д. после утверждения образца
D35: Вешалка флокированная с перекладиной, поворотный крючок, логотип 1 цвет, тираж 200 | E35: шт. | F35: 200 | G35: =Прайс!E36 | H35: =ROUND(F35*G35,0) | I35: 0 | J35: =ROUND(H35*(1-I35),0) | K35: =ROUND(J35*Прайс!$B$5,0) | L35: =J35+K35
D36: Доставка тиража по Москве | E36: рейс | F36: 1 | G36: =Прайс!E40 | H36: =ROUND(F36*G36,0) | I36: 0 | J36: =ROUND(H36*(1-I36),0) | K36: =ROUND(J36*Прайс!$B$5,0) | L36: =J36+K36 | P36: до Автозаводской, 18
D37: Тираж 500 шт. | E37: итого | H37: =SUM(H38:H39) | J37: =SUM(J38:J39) | K37: =SUM(K38:K39) | L37: =SUM(L38:L39) | M37: 15 р.д. после утверждения образца
D38: Вешалка флокированная с перекладиной, поворотный крючок, логотип 1 цвет, тираж 500 | E38: шт. | F38: 500 | G38: =Прайс!E37 | H38: =ROUND(F38*G38,0) | I38: 0 | J38: =ROUND(H38*(1-I38),0) | K38: =ROUND(J38*Прайс!$B$5,0) | L38: =J38+K38
D39: Доставка тиража по Москве | E39: рейс | F39: 1 | G39: =Прайс!E40 | H39: =ROUND(F39*G39,0) | I39: 0 | J39: =ROUND(H39*(1-I39),0) | K39: =ROUND(J39*Прайс!$B$5,0) | L39: =J39+K39 | P39: до Автозаводской, 18
D40: Тираж 1 000 шт. | E40: итого | H40: =SUM(H41:H42) | J40: =SUM(J41:J42) | K40: =SUM(K41:K42) | L40: =SUM(L41:L42) | M40: 30-40 р.д. после утверждения образца
D41: Вешалка флокированная с перекладиной, поворотный крючок, логотип 1 цвет, тираж 1000 | E41: шт. | F41: 1000 | G41: =Прайс!E38 | H41: =ROUND(F41*G41,0) | I41: 0 | J41: =ROUND(H41*(1-I41),0) | K41: =ROUND(J41*Прайс!$B$5,0) | L41: =J41+K41
D42: Доставка тиража по Москве | E42: рейс | F42: 1 | G42: =Прайс!E40 | H42: =ROUND(F42*G42,0) | I42: 0 | J42: =ROUND(H42*(1-I42),0) | K42: =ROUND(J42*Прайс!$B$5,0) | L42: =J42+K42 | P42: до Автозаводской, 18
D43: Образец с логотипом | E43: шт. | F43: 1 | G43: =Прайс!E39 | H43: =ROUND(F43*G43,0) | I43: 0 | J43: =ROUND(H43*(1-I43),0) | K43: =ROUND(J43*Прайс!$B$5,0) | L43: =J43+K43 | M43: 7 р.д.
A44: 7 | B44: Брендированные тишью | C44: Венеция | D44: Позиция ТЗ | N44: ="Аванс "&TEXT(Прайс!$B$7,"0%")&", остаток "&TEXT(1-Прайс!$B$7,"0%")&" после акта" | O44: =Прайс!$B$10&" мес." | P44: Бумага с нейтральным pH, гладкая матовая, без глянца. Перед тиражом проверяем на образце, что краска не переносится на ткань. Листы без фальцовки, пачки по 250-500 листов в защитной упаковке. Минимальный тираж 5 000 листов на формат. Дозаказ на тех же условиях, клише храним 12 месяцев.
D45: Тираж 10 000 листов 50 × 70 см и 10 000 листов 70 × 100 см | E45: итого | H45: =SUM(H46:H49) | J45: =SUM(J46:J49) | K45: =SUM(K46:K49) | L45: =SUM(L46:L49) | M45: 20 р.д. после утверждения образца
D46: Тишью 28 г/м² в цвет брендбука, 50 × 70 см, флексопечать паттерна 1 цвет Pantone | E46: лист | F46: 10000 | G46: =Прайс!E41 | H46: =ROUND(F46*G46,0) | I46: 0 | J46: =ROUND(H46*(1-I46),0) | K46: =ROUND(J46*Прайс!$B$5,0) | L46: =J46+K46 | P46: 50 × 70 см
D47: Тишью 28 г/м² в цвет брендбука, 70 × 100 см, флексопечать паттерна 1 цвет Pantone | E47: лист | F47: 10000 | G47: =Прайс!E42 | H47: =ROUND(F47*G47,0) | I47: 0 | J47: =ROUND(H47*(1-I47),0) | K47: =ROUND(J47*Прайс!$B$5,0) | L47: =J47+K47 | P47: 70 × 100 см
D48: Клише для флексопечати | E48: формат | F48: 2 | G48: =Прайс!E43 | H48: =ROUND(F48*G48,0) | I48: 0 | J48: =ROUND(H48*(1-I48),0) | K48: =ROUND(J48*Прайс!$B$5,0) | L48: =J48+K48 | P48: по клише на формат
D49: Доставка по Москве | E49: рейс | F49: 1 | G49: =Прайс!E45 | H49: =ROUND(F49*G49,0) | I49: 0 | J49: =ROUND(H49*(1-I49),0) | K49: =ROUND(J49*Прайс!$B$5,0) | L49: =J49+K49 | P49: до Автозаводской, 18
D50: Образцы с фирменной печатью | E50: формат | F50: 2 | G50: =Прайс!E44 | H50: =ROUND(F50*G50,0) | I50: 0 | J50: =ROUND(H50*(1-I50),0) | K50: =ROUND(J50*Прайс!$B$5,0) | L50: =J50+K50 | M50: 10 р.д. | P50: по образцу на формат
A51: 8 | B51: Брендированные кофры | C51: Венеция | D51: Позиция ТЗ | N51: ="Аванс "&TEXT(Прайс!$B$7,"0%")&", остаток "&TEXT(1-Прайс!$B$7,"0%")&" после акта" | O51: =Прайс!$B$10&" мес." | P51: Минимальный тираж 200 шт. Ткань с подтвержденным составом, перед тиражом проверяем перенос красителя на образце. Брендирование за единицу и печатная форма указаны отдельными строками. Брак меняем за свой счет.
D52: Тираж 200 шт. | E52: итого | H52: =SUM(H53:H56) | J52: =SUM(J53:J56) | K52: =SUM(K53:K56) | L52: =SUM(L53:L56) | M52: 20 р.д. после утверждения образца
D53: Кофр 150 × 60 × 10 см, саржа 100% хлопок 260 г/м², молния, ручки, кнопка, тираж 200 | E53: шт. | F53: 200 | G53: =Прайс!E46 | H53: =ROUND(F53*G53,0) | I53: 0 | J53: =ROUND(H53*(1-I53),0) | K53: =ROUND(J53*Прайс!$B$5,0) | L53: =J53+K53
D54: Шелкография логотипа 1 цвет, верхняя треть кофра | E54: шт. | F54: 200 | G54: =Прайс!E49 | H54: =ROUND(F54*G54,0) | I54: 0 | J54: =ROUND(H54*(1-I54),0) | K54: =ROUND(J54*Прайс!$B$5,0) | L54: =J54+K54
D55: Печатная форма для шелкографии | E55: компл. | F55: 1 | G55: =Прайс!E50 | H55: =ROUND(F55*G55,0) | I55: 0 | J55: =ROUND(H55*(1-I55),0) | K55: =ROUND(J55*Прайс!$B$5,0) | L55: =J55+K55
D56: Доставка по Москве | E56: рейс | F56: 1 | G56: =Прайс!E52 | H56: =ROUND(F56*G56,0) | I56: 0 | J56: =ROUND(H56*(1-I56),0) | K56: =ROUND(J56*Прайс!$B$5,0) | L56: =J56+K56 | P56: до Автозаводской, 18
D57: Тираж 500 шт. | E57: итого | H57: =SUM(H58:H61) | J57: =SUM(J58:J61) | K57: =SUM(K58:K61) | L57: =SUM(L58:L61) | M57: 25 р.д. после утверждения образца
D58: Кофр 150 × 60 × 10 см, саржа 100% хлопок 260 г/м², молния, ручки, кнопка, тираж 500 | E58: шт. | F58: 500 | G58: =Прайс!E47 | H58: =ROUND(F58*G58,0) | I58: 0 | J58: =ROUND(H58*(1-I58),0) | K58: =ROUND(J58*Прайс!$B$5,0) | L58: =J58+K58
D59: Шелкография логотипа 1 цвет, верхняя треть кофра | E59: шт. | F59: 500 | G59: =Прайс!E49 | H59: =ROUND(F59*G59,0) | I59: 0 | J59: =ROUND(H59*(1-I59),0) | K59: =ROUND(J59*Прайс!$B$5,0) | L59: =J59+K59
D60: Печатная форма для шелкографии | E60: компл. | F60: 1 | G60: =Прайс!E50 | H60: =ROUND(F60*G60,0) | I60: 0 | J60: =ROUND(H60*(1-I60),0) | K60: =ROUND(J60*Прайс!$B$5,0) | L60: =J60+K60
D61: Доставка по Москве | E61: рейс | F61: 1 | G61: =Прайс!E52 | H61: =ROUND(F61*G61,0) | I61: 0 | J61: =ROUND(H61*(1-I61),0) | K61: =ROUND(J61*Прайс!$B$5,0) | L61: =J61+K61 | P61: до Автозаводской, 18
D62: Тираж 1 000 шт. | E62: итого | H62: =SUM(H63:H66) | J62: =SUM(J63:J66) | K62: =SUM(K63:K66) | L62: =SUM(L63:L66) | M62: 35 р.д. после утверждения образца
D63: Кофр 150 × 60 × 10 см, саржа 100% хлопок 260 г/м², молния, ручки, кнопка, тираж 1000 | E63: шт. | F63: 1000 | G63: =Прайс!E48 | H63: =ROUND(F63*G63,0) | I63: 0 | J63: =ROUND(H63*(1-I63),0) | K63: =ROUND(J63*Прайс!$B$5,0) | L63: =J63+K63
D64: Шелкография логотипа 1 цвет, верхняя треть кофра | E64: шт. | F64: 1000 | G64: =Прайс!E49 | H64: =ROUND(F64*G64,0) | I64: 0 | J64: =ROUND(H64*(1-I64),0) | K64: =ROUND(J64*Прайс!$B$5,0) | L64: =J64+K64
D65: Печатная форма для шелкографии | E65: компл. | F65: 1 | G65: =Прайс!E50 | H65: =ROUND(F65*G65,0) | I65: 0 | J65: =ROUND(H65*(1-I65),0) | K65: =ROUND(J65*Прайс!$B$5,0) | L65: =J65+K65
D66: Доставка по Москве | E66: рейс | F66: 2 | G66: =Прайс!E52 | H66: =ROUND(F66*G66,0) | I66: 0 | J66: =ROUND(H66*(1-I66),0) | K66: =ROUND(J66*Прайс!$B$5,0) | L66: =J66+K66 | P66: до Автозаводской, 18
D67: Образец с логотипом | E67: шт. | F67: 1 | G67: =Прайс!E51 | H67: =ROUND(F67*G67,0) | I67: 0 | J67: =ROUND(H67*(1-I67),0) | K67: =ROUND(J67*Прайс!$B$5,0) | L67: =J67+K67 | M67: 10 р.д.
A68: 9 | B68: CGI & AI-студия, CGI-ролики | C68: Венеция, Времена Года, ЦДМ | D68: Позиция ТЗ | N68: ="100% по факту, оплата в течение "&Прайс!$B$8&" р.д. после акта, без аванса" | O68: =Прайс!$B$9&" мес." | P68: 2 круга правок на каждом этапе. Исключительные права на ролик и исходники передаем по договору. Музыка передается по лицензии на использование, стоковые и AI-материалы в объеме лицензий сервисов. AI-сервисы только на тарифах с коммерческим использованием.
D69: Новогодний CGI/AI-ролик 15 и 30 с, 16:9 и 9:16, без съемки | E69: итого | H69: =SUM(H70:H75) | J69: =SUM(J70:J75) | K69: =SUM(K70:K75) | L69: =SUM(L70:L75) | M69: 25 р.д. от утверждения брифа
D70: Креативная концепция, 2-3 направления | E70: этап | F70: 1 | G70: =Прайс!E53 | H70: =ROUND(F70*G70,0) | I70: =Прайс!$B$6 | J70: =ROUND(H70*(1-I70),0) | K70: =ROUND(J70*Прайс!$B$5,0) | L70: =J70+K70
D71: Раскадровка и аниматик | E71: этап | F71: 1 | G71: =Прайс!E54 | H71: =ROUND(F71*G71,0) | I71: =Прайс!$B$6 | J71: =ROUND(H71*(1-I71),0) | K71: =ROUND(J71*Прайс!$B$5,0) | L71: =J71+K71
D72: Производство мастер-версии 30 с, CGI и AI, 16:9 | E72: ролик | F72: 1 | G72: =Прайс!E55 | H72: =ROUND(F72*G72,0) | I72: =Прайс!$B$6 | J72: =ROUND(H72*(1-I72),0) | K72: =ROUND(J72*Прайс!$B$5,0) | L72: =J72+K72
D73: Версия 15 с на основе мастер-версии | E73: ролик | F73: 1 | G73: =Прайс!E56 | H73: =ROUND(F73*G73,0) | I73: =Прайс!$B$6 | J73: =ROUND(H73*(1-I73),0) | K73: =ROUND(J73*Прайс!$B$5,0) | L73: =J73+K73
D74: Адаптация в формат 9:16, версии 15 с и 30 с | E74: компл. | F74: 1 | G74: =Прайс!E57 | H74: =ROUND(F74*G74,0) | I74: =Прайс!$B$6 | J74: =ROUND(H74*(1-I74),0) | K74: =ROUND(J74*Прайс!$B$5,0) | L74: =J74+K74
D75: Монтаж, цветокоррекция, звук, лицензия на музыку | E75: этап | F75: 1 | G75: =Прайс!E58 | H75: =ROUND(F75*G75,0) | I75: =Прайс!$B$6 | J75: =ROUND(H75*(1-I75),0) | K75: =ROUND(J75*Прайс!$B$5,0) | L75: =J75+K75
A76: 10 | B76: Брендинг | C76: Венеция, Времена Года | D76: Позиция ТЗ | N76: ="100% по факту, оплата в течение "&Прайс!$B$8&" р.д. после акта, без аванса" | O76: =Прайс!$B$9&" мес." | P76: 3 концепции на старте, 2 круга правок на этапе. Исходники и исключительные права передаем, шрифты и стоки по их лицензиям.
D77: Айдентика сезонной кампании: KV, логотип, гайдлайн 10-15 стр., 5 носителей | E77: итого | H77: =SUM(H78:H82) | J77: =SUM(J78:J82) | K77: =SUM(K78:K82) | L77: =SUM(L78:L82) | M77: 20 р.д.
D78: Исследование и бриф | E78: этап | F78: 1 | G78: =Прайс!E62 | H78: =ROUND(F78*G78,0) | I78: =Прайс!$B$6 | J78: =ROUND(H78*(1-I78),0) | K78: =ROUND(J78*Прайс!$B$5,0) | L78: =J78+K78
D79: Три концепции: ключевой визуал и логотип кампании | E79: этап | F79: 1 | G79: =Прайс!E63 | H79: =ROUND(F79*G79,0) | I79: =Прайс!$B$6 | J79: =ROUND(H79*(1-I79),0) | K79: =ROUND(J79*Прайс!$B$5,0) | L79: =J79+K79 | P79: 3 концепции на первом показе
D80: Разработка выбранной концепции | E80: этап | F80: 1 | G80: =Прайс!E64 | H80: =ROUND(F80*G80,0) | I80: =Прайс!$B$6 | J80: =ROUND(H80*(1-I80),0) | K80: =ROUND(J80*Прайс!$B$5,0) | L80: =J80+K80
D81: Гайдлайн кампании 10-15 страниц | E81: шт. | F81: 1 | G81: =Прайс!E65 | H81: =ROUND(F81*G81,0) | I81: =Прайс!$B$6 | J81: =ROUND(H81*(1-I81),0) | K81: =ROUND(J81*Прайс!$B$5,0) | L81: =J81+K81
D82: Адаптация на носитель | E82: носитель | F82: 5 | G82: =Прайс!E66 | H82: =ROUND(F82*G82,0) | I82: =Прайс!$B$6 | J82: =ROUND(H82*(1-I82),0) | K82: =ROUND(J82*Прайс!$B$5,0) | L82: =J82+K82 | P82: баннер, пост, сторис, листовка, табличка
A83: 11 | B83: Дизайн макетов | C83: Времена Года, Венеция, Центральный рынок | D83: Позиция ТЗ | N83: ="100% по факту, оплата в течение "&Прайс!$B$8&" р.д. после акта, без аванса" | O83: =Прайс!$B$9&" мес." | P83: 2 круга правок. Тестовое задание выполняем бесплатно. Исходники AI, PSD, Figma.
D84: (1) Адаптация ключевого визуала на 10 форматов | E84: итого | H84: =SUM(H85:H85) | J84: =SUM(J85:J85) | K84: =SUM(K85:K85) | L84: =SUM(L85:L85) | M84: 2 р.д.
D85: Адаптация готового ключевого визуала, один формат | E85: формат | F85: 10 | G85: =Прайс!E67 | H85: =ROUND(F85*G85,0) | I85: =Прайс!$B$6 | J85: =ROUND(H85*(1-I85),0) | K85: =ROUND(J85*Прайс!$B$5,0) | L85: =J85+K85
D86: (2) Листовка А5 с нуля по брендбуку | E86: макет | F86: 1 | G86: =Прайс!E68 | H86: =ROUND(F86*G86,0) | I86: =Прайс!$B$6 | J86: =ROUND(H86*(1-I86),0) | K86: =ROUND(J86*Прайс!$B$5,0) | L86: =J86+K86 | M86: 3 р.д.
D87: (3) Почасовая ставка | E87: час | F87: 1 | G87: =Прайс!E69 | H87: =ROUND(F87*G87,0) | I87: =Прайс!$B$6 | J87: =ROUND(H87*(1-I87),0) | K87: =ROUND(J87*Прайс!$B$5,0) | L87: =J87+K87
A88: 12 | B88: Написание текстов | C88: Времена Года, Венеция | D88: Позиция ТЗ | N88: ="100% по факту, оплата в течение "&Прайс!$B$8&" р.д. после акта, без аванса" | O88: =Прайс!$B$9&" мес." | P88: Тестовое задание выполняем бесплатно. Срочный заказ день в день: доплата 50 процентов.
D89: (1) Пакет 12 постов в месяц | E89: итого | H89: =SUM(H90:H90) | J89: =SUM(J90:J90) | K89: =SUM(K90:K90) | L89: =SUM(L90:L90) | M89: Контент-план за 5 р.д. до начала месяца
D90: Пост для соцсетей | E90: пост | F90: 12 | G90: =Прайс!E70 | H90: =ROUND(F90*G90,0) | I90: =Прайс!$B$6 | J90: =ROUND(H90*(1-I90),0) | K90: =ROUND(J90*Прайс!$B$5,0) | L90: =J90+K90
D91: (2) Пресс-релиз об открытии магазина, 2000 знаков | E91: шт. | F91: 1 | G91: =Прайс!E71 | H91: =ROUND(F91*G91,0) | I91: =Прайс!$B$6 | J91: =ROUND(H91*(1-I91),0) | K91: =ROUND(J91*Прайс!$B$5,0) | L91: =J91+K91 | M91: 2 р.д., срочно 1 р.д.
D92: (3) Тексты для навигации и табличек, 20 позиций | E92: итого | H92: =SUM(H93:H93) | J92: =SUM(J93:J93) | K92: =SUM(K93:K93) | L92: =SUM(L93:L93) | M92: 2 р.д.
D93: Текст для навигации или таблички | E93: позиция | F93: 20 | G93: =Прайс!E72 | H93: =ROUND(F93*G93,0) | I93: =Прайс!$B$6 | J93: =ROUND(H93*(1-I93),0) | K93: =ROUND(J93*Прайс!$B$5,0) | L93: =J93+K93
A94: 13 | B94: Продюсер съемок | C94: Времена Года, Венеция | D94: Позиция ТЗ | N94: ="Аванс "&TEXT(Прайс!$B$11,"0%")&" на расходы подрядчиков, остаток в течение "&Прайс!$B$8&" р.д. после акта" | O94: =Прайс!$B$9&" мес." | P94: Релизы моделей на использование изображения входят в стоимость: 1 год, РФ, ваши каналы и объекты. Шире по договору. На моделей, свет, стилистов и реквизит скидка 10% не действует.
D95: Имиджевая съемка на объекте: 1 день 10 ч, 2 модели, итог 30 фото + ролик 30 с | E95: итого | H95: =SUM(H96:H108) | J95: =SUM(J96:J108) | K95: =SUM(K96:K108) | L95: =SUM(L96:L108) | M95: Подготовка 7 р.д., сдача 5 р.д. после съемки
D96: Продюсер съемки, смена | E96: смена | F96: 1 | G96: =Прайс!E74 | H96: =ROUND(F96*G96,0) | I96: =Прайс!$B$6 | J96: =ROUND(H96*(1-I96),0) | K96: =ROUND(J96*Прайс!$B$5,0) | L96: =J96+K96
D97: Фотограф, смена 10 ч | E97: смена | F97: 1 | G97: =Прайс!E75 | H97: =ROUND(F97*G97,0) | I97: =Прайс!$B$6 | J97: =ROUND(H97*(1-I97),0) | K97: =ROUND(J97*Прайс!$B$5,0) | L97: =J97+K97
D98: Видеограф с камерой и стабилизатором, смена 10 ч | E98: смена | F98: 1 | G98: =Прайс!E76 | H98: =ROUND(F98*G98,0) | I98: =Прайс!$B$6 | J98: =ROUND(H98*(1-I98),0) | K98: =ROUND(J98*Прайс!$B$5,0) | L98: =J98+K98
D99: Свет и грип, комплект на смену | E99: компл. | F99: 1 | G99: =Прайс!E77 | H99: =ROUND(F99*G99,0) | I99: 0 | J99: =ROUND(H99*(1-I99),0) | K99: =ROUND(J99*Прайс!$B$5,0) | L99: =J99+K99
D100: Модель, смена 10 ч, с релизом на использование изображения | E100: чел. | F100: 2 | G100: =Прайс!E78 | H100: =ROUND(F100*G100,0) | I100: 0 | J100: =ROUND(H100*(1-I100),0) | K100: =ROUND(J100*Прайс!$B$5,0) | L100: =J100+K100
D101: Стилист | E101: смена | F101: 1 | G101: =Прайс!E79 | H101: =ROUND(F101*G101,0) | I101: 0 | J101: =ROUND(H101*(1-I101),0) | K101: =ROUND(J101*Прайс!$B$5,0) | L101: =J101+K101
...

Sheet Прайс
A1: Прайс ООО «Хэнд-маркетинг» для вендор-листа ГК «Киевская площадь»
A2: Цены в рублях без НДС, НДС 22% начисляется сверху. Желтые ячейки: параметры условий, от них считаются КП и сводка.
A4: Параметр | B4: Значение | C4: Комментарий
A5: Ставка НДС, начисляется сверху | B5: 0.22 | C5: ООО «Хэнд-маркетинг» на ОСНО
A6: Скидка участника вендор-листа на работу агентства | B6: 0.1 | C6: Креатив, дизайн, тексты, CGI, съемка, концепции, эскизы, агентская комиссия. Подрядчики, аренда, персонал, производство: скидка от объема
A7: Аванс по производству и закупкам | B7: 0.7 | C7: Остаток после подписания акта
A8: Срок оплаты услуг после акта, рабочих дней | B8: 10 | C8: Услуги без аванса
A9: Фиксация цен на работу агентства, месяцев | B9: 6 | C9: С даты КП
A10: Срок действия цен производства и закупок, месяцев | B10: 3 | C10: С даты КП, дальше пересчет по ценам поставщиков
A11: Аванс по услугам с расходами на подрядчиков | B11: 0.5 | C11: Съемка с моделями, звук и свет, диджей, звукорежиссер, персонал
A12: Доплата за ночной монтаж 23:00-07:00 к стоимости монтажа | B12: 0.3 | C12: Для позиций 1, 23, 31
A13: Доплата за срочный выезд в течение 24 ч к стоимости смен | B13: 0.25 | C13: Для позиции 3
A14: Агентская комиссия на мероприятия | B14: 0.12 | C14: От суммы сметы мероприятия
A16: Поз. ТЗ | B16: Направление | C16: Услуга или изделие | D16: Ед. изм. | E16: Цена по прайсу, руб. без НДС | F16: Цена для вендор-листа, руб. без НДС | G16: Примечание
A17: 1 | B17: Рекламно-производственное агентство | C17: Лайтбокс односторонний 1,2 × 1,8 м, LED-подсветка, изготовление | D17: шт. | E17: 44000 | F17: =E17 | G17: Профиль алюминиевый, лицевая панель акрил, LED-модули
A18: 1 | B18: Рекламно-производственное агентство | C18: Монтаж лайтбокса на стену, подключение | D18: шт. | E18: 9000 | F18: =E18
A19: 1 | B19: Рекламно-производственное агентство | C19: Доплата за ночной монтаж 23:00-07:00, 30% к монтажу | D19: компл. | E19: 2700 | F19: =E19 | G19: Только если монтаж ночью
A20: 1 | B20: Рекламно-производственное агентство | C20: Доставка конструкций на объект по Москве | D20: рейс | E20: 6500 | F20: =E20
A21: 1 | B21: Рекламно-производственное агентство | C21: Объемная буква с внутренней подсветкой, высота 40 см | D21: знак | E21: По запросу | F21: По запросу | G21: Борт ПВХ или алюминий, лицо акрил, LED
A22: 1 | B22: Рекламно-производственное агентство | C22: Блок питания, коммутация, подложка вывески | D22: компл. | E22: По запросу | F22: По запросу
A23: 1 | B23: Рекламно-производственное агентство | C23: Монтаж вывески на высоте до 4 м, с вышкой | D23: компл. | E23: По запросу | F23: По запросу
A24: 1 | B24: Рекламно-производственное агентство | C24: Пленка с полноцветной печатью и ламинацией, оклейка витрины | D24: м² | E24: 2200 | F24: =E24 | G24: Печать 1440 dpi, ламинация матовая или глянцевая
A25: 1 | B25: Рекламно-производственное агентство | C25: Напольная фигура ПВХ 5 мм до 1,8 м, полноцветная печать, опора | D25: шт. | E25: 8500 | F25: =E25
A26: 1 | B26: Рекламно-производственное агентство | C26: Выезд на замер по Москве | D26: выезд | E26: Бесплатно | F26: Бесплатно | G26: Бесплатно. Выезд в течение 1 рабочего дня
A27: 3 | B27: Монтажные и демонтажные работы | C27: Монтажник, смена 8 ч, дневная | D27: чел.-смена | E27: 6800 | F27: =E27
A28: 3 | B28: Монтажные и демонтажные работы | C28: Монтажник, смена 8 ч, ночная | D28: чел.-смена | E28: 8800 | F28: =E28
A29: 3 | B29: Монтажные и демонтажные работы | C29: Грузовой автомобиль до 3 т, рейс по Москве | D29: рейс | E29: 8500 | F29: =E29
A30: 3 | B30: Монтажные и демонтажные работы | C30: Вывоз упаковки и мусора | D30: рейс | E30: 6500 | F30: =E30
A31: 3 | B31: Монтажные и демонтажные работы | C31: Аренда вышки-туры до 6 м с доставкой | D31: сутки | E31: 4800 | F31: =E31 | G31: Ручной инструмент входит в ставку смены
A32: 5 | B32: Пластиковые карты | C32: Карта ПВХ 0,76 мм CR80, печать 4+4, матовая ламинация, фольга, HiCo, лазерная нумерация | D32: шт. | E32: 38 | F32: =E32
A33: 5 | B33: Пластиковые карты | C33: Клише для тиснения фольгой, подготовка к печати | D33: компл. | E33: 6000 | F33: =E33 | G33: Один раз на макет
A34: 5 | B34: Пластиковые карты | C34: Пробный образец карты с отделкой и персонализацией | D34: компл. | E34: 9500 | F34: =E34 | G34: Засчитывается в тираж
A35: 5 | B35: Пластиковые карты | C35: Доставка тиража по Москве | D35: рейс | E35: 2500 | F35: =E35
A36: 6 | B36: Брендированные вешалки | C36: Вешалка флокированная с перекладиной, поворотный крючок, логотип 1 цвет, тираж 200 | D36: шт. | E36: 290 | F36: =E36 | G36: Цвет флока: ближайший из наличия
A37: 6 | B37: Брендированные вешалки | C37: Вешалка флокированная с перекладиной, поворотный крючок, логотип 1 цвет, тираж 500 | D37: шт. | E37: 240 | F37: =E37 | G37: Цвет флока: ближайший из наличия
A38: 6 | B38: Брендированные вешалки | C38: Вешалка флокированная с перекладиной, поворотный крючок, логотип 1 цвет, тираж 1000 | D38: шт. | E38: 210 | F38: =E38 | G38: Цвет флока по Pantone брендбука
A39: 6 | B39: Брендированные вешалки | C39: Образец вешалки с логотипом | D39: шт. | E39: 3500 | F39: =E39
A40: 6 | B40: Брендированные вешалки | C40: Доставка тиража по Москве | D40: рейс | E40: 6500 | F40: =E40
A41: 7 | B41: Брендированные тишью | C41: Тишью 28 г/м² в цвет брендбука, 50 × 70 см, флексопечать паттерна 1 цвет Pantone | D41: лист | E41: 32 | F41: =E41
A42: 7 | B42: Брендированные тишью | C42: Тишью 28 г/м² в цвет брендбука, 70 × 100 см, флексопечать паттерна 1 цвет Pantone | D42: лист | E42: 54 | F42: =E42
A43: 7 | B43: Брендированные тишью | C43: Клише для флексопечати | D43: формат | E43: 9000 | F43: =E43 | G43: Один раз на макет и формат
A44: 7 | B44: Брендированные тишью | C44: Образец с фирменной печатью | D44: формат | E44: 6500 | F44: =E44
A45: 7 | B45: Брендированные тишью | C45: Доставка по Москве | D45: рейс | E45: 6500 | F45: =E45
A46: 8 | B46: Брендированные кофры | C46: Кофр 150 × 60 × 10 см, саржа 100% хлопок 260 г/м², молния, ручки, кнопка, тираж 200 | D46: шт. | E46: 3100 | F46: =E46
A47: 8 | B47: Брендированные кофры | C47: Кофр 150 × 60 × 10 см, саржа 100% хлопок 260 г/м², молния, ручки, кнопка, тираж 500 | D47: шт. | E47: 2700 | F47: =E47
A48: 8 | B48: Брендированные кофры | C48: Кофр 150 × 60 × 10 см, саржа 100% хлопок 260 г/м², молния, ручки, кнопка, тираж 1000 | D48: шт. | E48: 2350 | F48: =E48
A49: 8 | B49: Брендированные кофры | C49: Шелкография логотипа 1 цвет, верхняя треть кофра | D49: шт. | E49: 85 | F49: =E49
A50: 8 | B50: Брендированные кофры | C50: Печатная форма для шелкографии | D50: компл. | E50: 3500 | F50: =E50 | G50: Один раз на макет
A51: 8 | B51: Брендированные кофры | C51: Образец кофра с логотипом | D51: шт. | E51: 9500 | F51: =E51
A52: 8 | B52: Брендированные кофры | C52: Доставка по Москве | D52: рейс | E52: 6500 | F52: =E52 | G52: До 500 шт. в рейс
A53: 9 | B53: CGI & AI-студия, CGI-ролики | C53: Креативная концепция, 2-3 направления | D53: этап | E53: 55000 | F53: =ROUND(E53*(1-Прайс!$B$6),0) | G53: 2 круга правок
A54: 9 | B54: CGI & AI-студия, CGI-ролики | C54: Раскадровка и аниматик | D54: этап | E54: 65000 | F54: =ROUND(E54*(1-Прайс!$B$6),0) | G54: 2 круга правок
A55: 9 | B55: CGI & AI-студия, CGI-ролики | C55: Производство мастер-версии 30 с, CGI и AI, 16:9 | D55: ролик | E55: 340000 | F55: =ROUND(E55*(1-Прайс!$B$6),0) | G55: 2 круга правок
A56: 9 | B56: CGI & AI-студия, CGI-ролики | C56: Версия 15 с на основе мастер-версии | D56: ролик | E56: 45000 | F56: =ROUND(E56*(1-Прайс!$B$6),0)
A57: 9 | B57: CGI & AI-студия, CGI-ролики | C57: Адаптация в формат 9:16, версии 15 с и 30 с | D57: компл. | E57: 65000 | F57: =ROUND(E57*(1-Прайс!$B$6),0)
A58: 9 | B58: CGI & AI-студия, CGI-ролики | C58: Монтаж, цветокоррекция, звук, лицензия на музыку | D58: этап | E58: 70000 | F58: =ROUND(E58*(1-Прайс!$B$6),0) | G58: 2 круга правок
A59: 9 | B59: CGI & AI-студия, CGI-ролики | C59: Секунда CGI/3D-анимации | D59: сек. | E59: 16000 | F59: =ROUND(E59*(1-Прайс!$B$6),0) | G59: Прайс для разовых задач
A60: 9 | B60: CGI & AI-студия, CGI-ролики | C60: Секунда AI-видео с доработкой и зачисткой артефактов | D60: сек. | E60: 9000 | F60: =ROUND(E60*(1-Прайс!$B$6),0) | G60: Прайс для разовых задач
A61: 9 | B61: CGI & AI-студия, CGI-ролики | C61: Статичный AI-визуал, финальное качество | D61: шт. | E61: 14000 | F61: =ROUND(E61*(1-Прайс!$B$6),0) | G61: Прайс для разовых задач
A62: 10 | B62: Брендинг | C62: Исследование и бриф | D62: этап | E62: 40000 | F62: =ROUND(E62*(1-Прайс!$B$6),0)
A63: 10 | B63: Брендинг | C63: Три концепции: ключевой визуал и логотип кампании | D63: этап | E63: 130000 | F63: =ROUND(E63*(1-Прайс!$B$6),0) | G63: 2 круга правок
A64: 10 | B64: Брендинг | C64: Разработка выбранной концепции | D64: этап | E64: 95000 | F64: =ROUND(E64*(1-Прайс!$B$6),0) | G64: 2 круга правок
A65: 10 | B65: Брендинг | C65: Гайдлайн кампании 10-15 страниц | D65: шт. | E65: 65000 | F65: =ROUND(E65*(1-Прайс!$B$6),0)
A66: 10 | B66: Брендинг | C66: Адаптация на носитель | D66: носитель | E66: 9000 | F66: =ROUND(E66*(1-Прайс!$B$6),0)
A67: 11 | B67: Дизайн макетов | C67: Адаптация готового ключевого визуала, один формат | D67: формат | E67: 2900 | F67: =ROUND(E67*(1-Прайс!$B$6),0) | G67: 2 круга правок
A68: 11 | B68: Дизайн макетов | C68: Макет с нуля по брендбуку (листовка А5) | D68: макет | E68: 19000 | F68: =ROUND(E68*(1-Прайс!$B$6),0) | G68: 2 круга правок
A69: 11 | B69: Дизайн макетов | C69: Час работы дизайнера | D69: час | E69: 3500 | F69: =ROUND(E69*(1-Прайс!$B$6),0)
A70: 12 | B70: Написание текстов | C70: Пост для соцсетей | D70: пост | E70: 2800 | F70: =ROUND(E70*(1-Прайс!$B$6),0) | G70: 2 круга правок
A71: 12 | B71: Написание текстов | C71: Пресс-релиз до 2000 знаков | D71: шт. | E71: 11000 | F71: =ROUND(E71*(1-Прайс!$B$6),0) | G71: 2 круга правок
A72: 12 | B72: Написание текстов | C72: Текст для навигации или таблички | D72: позиция | E72: 600 | F72: =ROUND(E72*(1-Прайс!$B$6),0)
A73: 12 | B73: Написание текстов | C73: 1000 знаков текста | D73: 1000 зн. | E73: 2500 | F73: =ROUND(E73*(1-Прайс!$B$6),0) | G73: Прайс для разовых задач
A74: 13 | B74: Продюсер съемок | C74: Продюсер съемки, смена | D74: смена | E74: 38000 | F74: =ROUND(E74*(1-Прайс!$B$6),0) | G74: Отдельно: 10 процентов от сметы съемки
A75: 13 | B75: Продюсер съемок | C75: Фотограф, смена 10 ч | D75: смена | E75: 48000 | F75: =ROUND(E75*(1-Прайс!$B$6),0)
A76: 13 | B76: Продюсер съемок | C76: Видеограф с камерой и стабилизатором, смена 10 ч | D76: смена | E76: 58000 | F76: =ROUND(E76*(1-Прайс!$B$6),0)
A77: 13 | B77: Продюсер съемок | C77: Свет и грип, комплект на смену | D77: компл. | E77: 38000 | F77: =E77
A78: 13 | B78: Продюсер съемок | C78: Модель, смена 10 ч, с релизом на использование изображения | D78: чел. | E78: 48000 | F78: =E78 | G78: Релиз на срок и территорию по договору
A79: 13 | B79: Продюсер съемок | C79: Стилист | D79: смена | E79: 27000 | F79: =E79
A80: 13 | B80: Продюсер съемок | C80: Визажист | D80: смена | E80: 22000 | F80: =E80
A81: 13 | B81: Продюсер съемок | C81: Реквизит, закупка и аренда | D81: компл. | E81: 32000 | F81: =E81
A82: 13 | B82: Продюсер съемок | C82: Ассистент | D82: смена | E82: 9000 | F82: =E82
A83: 13 | B83: Продюсер съемок | C83: Транспорт группы и техники | D83: компл. | E83: 13000 | F83: =E83
A84: 13 | B84: Продюсер съемок | C84: Ретушь фотографии | D84: кадр | E84: 1600 | F84: =ROUND(E84*(1-Прайс!$B$6),0)
A85: 13 | B85: Продюсер съемок | C85: Монтаж ролика 30 с, цвет, звук | D85: ролик | E85: 45000 | F85: =ROUND(E85*(1-Прайс!$B$6),0)
A86: 13 | B86: Продюсер съемок | C86: Питание группы | D86: компл. | E86: 16000 | F86: =E86
A87: 14 | B87: Фотограф | C87: Фотограф, репортаж, час (минимум 2 ч) | D87: час | E87: 7000 | F87: =ROUND(E87*(1-Прайс!$B$6),0) | G87: 35 обработанных кадров за час
A88: 14 | B88: Фотограф | C88: Фотограф, день 10 ч | D88: день | E88: 55000 | F88: =ROUND(E88*(1-Прайс!$B$6),0) | G88: Прайс
A89: 14 | B89: Фотограф | C89: Интерьерная съемка, обработанный кадр | D89: кадр | E89: 2300 | F89: =ROUND(E89*(1-Прайс!$B$6),0) | G89: Свет фотографа
A90: 14 | B90: Фотограф | C90: Предметная съемка на белом фоне, кадр | D90: кадр | E90: 1300 | F90: =ROUND(E90*(1-Прайс!$B$6),0) | G90: Вырез фона включен
A91: 15 | B91: Видеограф | C91: Видеограф, час (минимум 2 ч) | D91: час | E91: 7500 | F91: =ROUND(E91*(1-Прайс!$B$6),0)
A92: 15 | B92: Видеограф | C92: Видеограф, день 10 ч | D92: день | E92: 60000 | F92: =ROUND(E92*(1-Прайс!$B$6),0) | G92: Прайс
A93: 15 | B93: Видеограф | C93: Монтаж, минута готового видео | D93: мин. | E93: 18000 | F93: =ROUND(E93*(1-Прайс!$B$6),0) | G93: Прайс
A94: 15 | B94: Видеограф | C94: Отчетный ролик 60-90 с, 16:9, 4K | D94: ролик | E94: 28000 | F94: =ROUND(E94*(1-Прайс!$B$6),0)
A95: 15 | B95: Видеограф | C95: Reels 15-30 с, 9:16, сдача в день мероприятия | D95: шт. | E95: 9000 | F95: =ROUND(E95*(1-Прайс!$B$6),0)
A96: 15 | B96: Видеограф | C96: Съемка FPV-дроном в помещении, до 2 ч | D96: выезд | E96: 30000 | F96: =E96 | G96: Внутри объекта, без разрешения на воздушное пространство
A97: 16 | B97: Мерч, корпоративные подарки | C97: Худи, хлопок с начесом от 320 г/м², вышивка 10 × 10 см, тираж 100 | D97: шт. | E97: По запросу | F97: По запросу
A98: 16 | B98: Мерч, корпоративные подарки | C98: Худи, хлопок с начесом от 320 г/м², вышивка 10 × 10 см, тираж 500 | D98: шт. | E98: По запросу | F98: По запросу
A99: 16 | B99: Мерч, корпоративные подарки | C99: Шопер, хлопок 220 г/м², шелкография 1 цвет, тираж 100 | D99: шт. | E99: 590 | F99: =E99
A100: 16 | B100: Мерч, корпоративные подарки | C100: Шопер, хлопок 220 г/м², шелкография 1 цвет, тираж 500 | D100: шт. | E100: 390 | F100: =E100
A101: 16 | B101: Мерч, корпоративные подарки | C101: Термокружка 350 мл, лазерная гравировка, тираж 100 | D101: шт. | E101: 990 | F101: =E101
A102: 16 | B102: Мерч, корпоративные подарки | C102: Термокружка 350 мл, лазерная гравировка, тираж 500 | D102: шт. | E102: 790 | F102: =E102
...
